{
  "version": "0.3.14-fixed",
  "steps": [
    {
      "stepType": "CreateModel",
      "name": "Starter",
      "embedded": false
    },
    {
      "stepType": "CreateField",
      "model": "Starter",
      "name": "id",
      "type": {
        "Base": "String"
      },
      "arity": "required",
      "isUnique": false,
      "id": {
        "strategy": "Auto",
        "sequence": null
      },
      "default": {
        "Expression": ["cuid", "String", []]
      }
    },
    {
      "stepType": "CreateField",
      "model": "Starter",
      "name": "createdAt",
      "type": {
        "Base": "DateTime"
      },
      "arity": "required",
      "isUnique": false,
      "default": {
        "Expression": ["now", "DateTime", []]
      }
    },
    {
      "stepType": "CreateField",
      "model": "Starter",
      "name": "updatedAt",
      "type": {
        "Base": "DateTime"
      },
      "arity": "required",
      "isUnique": false
    },
    {
      "stepType": "CreateField",
      "model": "Starter",
      "name": "repo",
      "type": {
        "Base": "String"
      },
      "arity": "required",
      "isUnique": false
    },
    {
      "stepType": "CreateField",
      "model": "Starter",
      "name": "owner",
      "type": {
        "Base": "String"
      },
      "arity": "required",
      "isUnique": false
    },
    {
      "stepType": "CreateField",
      "model": "Starter",
      "name": "path",
      "type": {
        "Base": "String"
      },
      "arity": "required",
      "isUnique": false
    },
    {
      "stepType": "CreateField",
      "model": "Starter",
      "name": "ref",
      "type": {
        "Base": "String"
      },
      "arity": "required",
      "isUnique": false
    },
    {
      "stepType": "CreateField",
      "model": "Starter",
      "name": "name",
      "type": {
        "Base": "String"
      },
      "arity": "required",
      "isUnique": false
    },
    {
      "stepType": "CreateField",
      "model": "Starter",
      "name": "description",
      "type": {
        "Base": "String"
      },
      "arity": "optional",
      "isUnique": false
    },
    {
      "stepType": "CreateField",
      "model": "Starter",
      "name": "dependencies",
      "type": {
        "Base": "String"
      },
      "arity": "list",
      "isUnique": false
    }
  ]
}
